interaction/Iterable.py
interaction/ProgressBar.py
interaction/__init__.py
interaction/colour.py
interaction/map.py
interaction-1.3.dist-info/LICENSE
interaction-1.3.dist-info/METADATA
interaction-1.3.dist-info/WHEEL
interaction-1.3.dist-info/top_level.txt
interaction-1.3.dist-info/RECORD
